random_string_detector/__init__.py
random_string_detector/detector.py
random_string_detector/preprocessing.py
random_string_detector/bigrams/__init__.py
random_string_detector/bigrams/english.py
random_string_detector/bigrams/french.py
random_string_detector/bigrams/portuguese.py
random_string_detector-1.1.1.dist-info/METADATA
random_string_detector-1.1.1.dist-info/WHEEL
random_string_detector-1.1.1.dist-info/licenses/LICENSE
random_string_detector-1.1.1.dist-info/RECORD
