Metadata-Version: 2.4
Name: random-string-detector
Version: 1.1.1
Summary: A package for random string detection
Project-URL: Homepage, https://github.com/mehmedkadric/random-string-detector
Project-URL: Bug Tracker, https://github.com/mehmedkadric/random-string-detector/issues
Author-email: Mehmed Kadric <kadricze@gmail.com>
License-File: LICENSE
Classifier: License :: OSI Approved :: MIT License
Classifier: Operating System :: OS Independent
Classifier: Programming Language :: Python :: 3
Requires-Python: >=3.9
